Metadata-Version: 1.0
Name: nr.futures
Version: 1.0.1
Summary: A convenient threading based future implementation compatible with Python 2 and 3.
Home-page: https://github.com/NiklasRosenstein-Python/nr.futures
Author: Niklas Rosenstein
Author-email: rosensteinniklas@gmail.com
License: MIT
Platform: UNKNOWN
